keridht/__init__.py
keridht/__main__.py
keridht/app.py
keridht/base.py
keridht/cli.py
keridht/client.py
keridht/daemon.py
keridht/ipl.py
keridht/kes.py
keridht/methods.py
keridht/msg.py
keridht/node.py
keridht/testing.py
keridht/utility.py
keridht-0.0.1.dist-info/LICENSE
keridht-0.0.1.dist-info/METADATA
keridht-0.0.1.dist-info/WHEEL
keridht-0.0.1.dist-info/entry_points.txt
keridht-0.0.1.dist-info/top_level.txt
keridht-0.0.1.dist-info/RECORD
