Metadata-Version: 2.1
Name: keridht
Version: 0.0.1
Summary: KERI DHT Discovery
Home-page: https://github.com/decentralized-identity/keri-dht-py
Author: 
Author-email: 
License: Apache Software License 2.0
Project-URL: Documentation, https://keridht.readthedocs.io/
Project-URL: Changelog, https://keridht.readthedocs.io/en/latest/changelog.html
Project-URL: Issue Tracker, https://github.com/decentralized-identity/keri-dht-py/issues
Platform: UNKNOWN
Classifier: Development Status :: 3 - Alpha
Classifier: Intended Audience :: Developers
Classifier: License :: OSI Approved :: Apache Software License
Classifier: Operating System :: Unix
Classifier: Operating System :: POSIX
Classifier: Operating System :: Microsoft :: Windows
Classifier: Programming Language :: Python :: 3.9
Classifier: Programming Language :: Python :: Implementation :: CPython
Classifier: Topic :: Utilities
Requires-Python: >=3.9.4
Requires-Dist: lmdb (>=1.1.1)
Requires-Dist: pysodium (>=0.7.7)
Requires-Dist: blake3 (>=0.1.8)
Requires-Dist: msgpack (>=1.0.2)
Requires-Dist: cbor2 (>=5.2.0)
Requires-Dist: hio (>=0.3.2)
